ruth_tts_transformer/__init__.py
ruth_tts_transformer/api.py
ruth_tts_transformer/ruth_tts/__init__.py
ruth_tts_transformer/ruth_tts/api.py
ruth_tts_transformer/ruth_tts/do_tts.py
ruth_tts_transformer/ruth_tts/eval.py
ruth_tts_transformer/ruth_tts/get_conditioning_latents.py
ruth_tts_transformer/ruth_tts/is_this_from_ruth.py
ruth_tts_transformer/ruth_tts/read.py
ruth_tts_transformer/ruth_tts/models/__init__.py
ruth_tts_transformer/ruth_tts/models/arch_util.py
ruth_tts_transformer/ruth_tts/models/autoregressive.py
ruth_tts_transformer/ruth_tts/models/classifier.py
ruth_tts_transformer/ruth_tts/models/clvp.py
ruth_tts_transformer/ruth_tts/models/cvvp.py
ruth_tts_transformer/ruth_tts/models/diffusion_decoder.py
ruth_tts_transformer/ruth_tts/models/random_latent_generator.py
ruth_tts_transformer/ruth_tts/models/transformer.py
ruth_tts_transformer/ruth_tts/models/vocoder.py
ruth_tts_transformer/ruth_tts/models/xtransformers.py
ruth_tts_transformer/ruth_tts/utils/__init__.py
ruth_tts_transformer/ruth_tts/utils/audio.py
ruth_tts_transformer/ruth_tts/utils/diffusion.py
ruth_tts_transformer/ruth_tts/utils/samples_generator.py
ruth_tts_transformer/ruth_tts/utils/stft.py
ruth_tts_transformer/ruth_tts/utils/text.py
ruth_tts_transformer/ruth_tts/utils/tokenizer.py
ruth_tts_transformer/ruth_tts/utils/typical_sampling.py
ruth_tts_transformer/ruth_tts/utils/wav2vec_alignment.py
ruth_tts_converter-0.0.2.dist-info/METADATA
ruth_tts_converter-0.0.2.dist-info/WHEEL
ruth_tts_converter-0.0.2.dist-info/entry_points.txt
ruth_tts_converter-0.0.2.dist-info/top_level.txt
ruth_tts_converter-0.0.2.dist-info/RECORD
